[
  {
    "id": 1,
    "image": "/src/assets/demo-app (1).webp",
    "title": "Chatify Messenger",
    "companyName": "WaveSoft Technologies",
    "description": "Connect with friends and family instantly with real-time messaging and voice calls.",
    "size": 45,
    "reviews": 126000,
    "ratingAvg": 4.6,
    "downloads": 9,
    "ratings": [
      { "name": "1 star", "count": 3200 },
      { "name": "2 star", "count": 5800 },
      { "name": "3 star", "count": 11000 },
      { "name": "4 star", "count": 32000 },
      { "name": "5 star", "count": 75000 }
    ]
  },
  {
    "id": 2,
    "image": "/src/assets/demo-app (2).webp",
    "title": "TaskPro",
    "companyName": "NextGen Labs",
    "description": "Organize your work and personal life with smart task lists, reminders, and progress tracking.",
    "size": 32,
    "reviews": 87000,
    "ratingAvg": 4.4,
    "downloads": 9,
    "ratings": [
      { "name": "1 star", "count": 2100 },
      { "name": "2 star", "count": 4500 },
      { "name": "3 star", "count": 9200 },
      { "name": "4 star", "count": 27000 },
      { "name": "5 star", "count": 44200 }
    ]
  },
  {
    "id": 3,
    "image": "/src/assets/demo-app (3).webp",
    "title": "FitLife",
    "companyName": "ZenTech",
    "description": "Your ultimate fitness companion with personalized workouts, diet plans, and progress analytics.",
    "size": 54,
    "reviews": 64000,
    "ratingAvg": 4.8,
    "downloads": 9,
    "ratings": [
      { "name": "1 star", "count": 1200 },
      { "name": "2 star", "count": 2500 },
      { "name": "3 star", "count": 4100 },
      { "name": "4 star", "count": 16000 },
      { "name": "5 star", "count": 40200 }
    ]
  },
  {
    "id": 4,
    "image": "/src/assets/demo-app (4).webp",
    "title": "Musicly",
    "companyName": "SoundFlow Ltd",
    "description": "Stream your favourite songs, create playlists, and discover trending artists worldwide.",
    "size": 60,
    "reviews": 210000,
    "ratingAvg": 4.7,
    "downloads": 9,
    "ratings": [
      { "name": "1 star", "count": 6200 },
      { "name": "2 star", "count": 7800 },
      { "name": "3 star", "count": 16000 },
      { "name": "4 star", "count": 47000 },
      { "name": "5 star", "count": 133000 }
    ]
  },
  {
    "id": 5,
    "image": "/src/assets/demo-app (5).webp",
    "title": "PhotoEdit Pro",
    "companyName": "PixelWorks Studio",
    "description": "Edit photos like a pro with AI filters, background remover, and beauty enhancements.",
    "size": 76,
    "reviews": 310000,
    "ratingAvg": 4.5,
    "downloads": 9,
    "ratings": [
      { "name": "1 star", "count": 8200 },
      { "name": "2 star", "count": 11000 },
      { "name": "3 star", "count": 25000 },
      { "name": "4 star", "count": 77000 },
      { "name": "5 star", "count": 189000 }
    ]
  },
  {
    "id": 6,
    "image": "/src/assets/demo-app (6).webp",
    "title": "LearnHub",
    "companyName": "EduSoft Global",
    "description": "Interactive learning platform offering free and premium online courses from top instructors.",
    "size": 40,
    "reviews": 156000,
    "ratingAvg": 4.9,
    "downloads": 9,
    "ratings": [
      { "name": "1 star", "count": 1500 },
      { "name": "2 star", "count": 2100 },
      { "name": "3 star", "count": 4100 },
      { "name": "4 star", "count": 18000 },
      { "name": "5 star", "count": 130300 }
    ]
  },
  {
    "id": 7,
    "image": "/src/assets/demo-app (1).webp",
    "title": "FinTrack",
    "companyName": "SmartMoney Inc.",
    "description": "Track your expenses, set budgets, and grow savings with AI-based financial insights.",
    "size": 35,
    "reviews": 54000,
    "ratingAvg": 4.3,
    "downloads": 9,
    "ratings": [
      { "name": "1 star", "count": 2300 },
      { "name": "2 star", "count": 4300 },
      { "name": "3 star", "count": 8800 },
      { "name": "4 star", "count": 15000 },
      { "name": "5 star", "count": 23400 }
    ]
  },
  {
    "id": 8,
    "image": "/src/assets/demo-app (2).webp",
    "title": "WeatherWise",
    "companyName": "ClimaTech",
    "description": "Real-time weather updates, forecasts, and storm alerts with stunning visuals.",
    "size": 28,
    "reviews": 88000,
    "ratingAvg": 4.2,
    "downloads": 9,
    "ratings": [
      { "name": "1 star", "count": 4000 },
      { "name": "2 star", "count": 6300 },
      { "name": "3 star", "count": 10500 },
      { "name": "4 star", "count": 24000 },
      { "name": "5 star", "count": 43000 }
    ]
  },
  {
    "id": 9,
    "image": "/src/assets/demo-app (3).webp",
    "title": "TravelGo",
    "companyName": "TripZen Pvt. Ltd.",
    "description": "Plan trips, book hotels, and discover new destinations with AI travel recommendations.",
    "size": 67,
    "reviews": 113000,
    "ratingAvg": 4.6,
    "downloads": 9,
    "ratings": [
      { "name": "1 star", "count": 3100 },
      { "name": "2 star", "count": 5900 },
      { "name": "3 star", "count": 10500 },
      { "name": "4 star", "count": 33000 },
      { "name": "5 star", "count": 60600 }
    ]
  },
  {
    "id": 10,
    "image": "/src/assets/demo-app (4).webp",
    "title": "GameLand",
    "companyName": "PixelFun Studio",
    "description": "Discover and play trending mobile games in one place — download, compete, and win rewards.",
    "size": 120,
    "reviews": 400000,
    "ratingAvg": 4.8,
    "downloads": 9,
    "ratings": [
      { "name": "1 star", "count": 12000 },
      { "name": "2 star", "count": 18000 },
      { "name": "3 star", "count": 32000 },
      { "name": "4 star", "count": 96000 },
      { "name": "5 star", "count": 244000 }
    ]
  },
  {
    "id": 11,
    "image": "/src/assets/demo-app (5).webp",
    "title": "Readly",
    "companyName": "BookNest Co.",
    "description": "Thousands of ebooks and audiobooks in one place. Read offline and sync across devices.",
    "size": 82,
    "reviews": 67000,
    "ratingAvg": 4.4,
    "downloads": 9,
    "ratings": [
      { "name": "1 star", "count": 2600 },
      { "name": "2 star", "count": 4900 },
      { "name": "3 star", "count": 9100 },
      { "name": "4 star", "count": 19000 },
      { "name": "5 star", "count": 31400 }
    ]
  },
  {
    "id": 12,
    "image": "/src/assets/demo-app (6).webp",
    "title": "Shopio",
    "companyName": "RetailX",
    "description": "Your one-stop shopping app with exclusive offers, fast delivery, and secure payments.",
    "size": 56,
    "reviews": 286000,
    "ratingAvg": 4.6,
    "downloads": 8,
    "ratings": [
      { "name": "1 star", "count": 7200 },
      { "name": "2 star", "count": 9600 },
      { "name": "3 star", "count": 18000 },
      { "name": "4 star", "count": 51000 },
      { "name": "5 star", "count": 200000 }
    ]
  },
  {
    "id": 13,
    "image": "/src/assets/demo-app (1).webp",
    "title": "MediCare",
    "companyName": "HealthLink Digital",
    "description": "Consult doctors online, track prescriptions, and manage your health reports securely.",
    "size": 49,
    "reviews": 88000,
    "ratingAvg": 4.7,
    "downloads": 6,
    "ratings": [
      { "name": "1 star", "count": 2100 },
      { "name": "2 star", "count": 3100 },
      { "name": "3 star", "count": 6200 },
      { "name": "4 star", "count": 23000 },
      { "name": "5 star", "count": 53600 }
    ]
  },
  {
    "id": 14,
    "image": "/src/assets/demo-app (2).webp",
    "title": "CookMate",
    "companyName": "FoodFusion Studio",
    "description": "Find recipes, watch tutorials, and manage grocery lists in one smart kitchen app.",
    "size": 42,
    "reviews": 120000,
    "ratingAvg": 4.5,
    "downloads": 9,
    "ratings": [
      { "name": "1 star", "count": 3800 },
      { "name": "2 star", "count": 5200 },
      { "name": "3 star", "count": 8900 },
      { "name": "4 star", "count": 25000 },
      { "name": "5 star", "count": 77000 }
    ]
  },
  {
    "id": 15,
    "image": "/src/assets/demo-app (3).webp",
    "title": "DriveEasy",
    "companyName": "AutoTech Labs",
    "description": "Monitor your car’s performance, mileage, and maintenance schedule with AI insights.",
    "size": 70,
    "reviews": 54000,
    "ratingAvg": 4.3,
    "downloads": 3,
    "ratings": [
      { "name": "1 star", "count": 2500 },
      { "name": "2 star", "count": 4300 },
      { "name": "3 star", "count": 7600 },
      { "name": "4 star", "count": 16000 },
      { "name": "5 star", "count": 23600 }
    ]
  },
  {
    "id": 16,
    "image": "/src/assets/demo-app (4).webp",
    "title": "StudyNow",
    "companyName": "EduMaster",
    "description": "Flashcards, quizzes, and notes — the ultimate student productivity toolkit.",
    "size": 36,
    "reviews": 110000,
    "ratingAvg": 4.8,
    "downloads": 7,
    "ratings": [
      { "name": "1 star", "count": 1800 },
      { "name": "2 star", "count": 2700 },
      { "name": "3 star", "count": 5200 },
      { "name": "4 star", "count": 18000 },
      { "name": "5 star", "count": 82300 }
    ]
  },
  {
    "id": 17,
    "image": "/src/assets/demo-app (5).webp",
    "title": "Relaxify",
    "companyName": "CalmSpace Studio",
    "description": "Meditation, sleep sounds, and stress relief sessions for mental well-being.",
    "size": 50,
    "reviews": 145000,
    "ratingAvg": 4.9,
    "downloads": 1,
    "ratings": [
      { "name": "1 star", "count": 1200 },
      { "name": "2 star", "count": 1900 },
      { "name": "3 star", "count": 3100 },
      { "name": "4 star", "count": 18000 },
      { "name": "5 star", "count": 120800 }
    ]
  },
  {
    "id": 18,
    "image": "/src/assets/demo-app (6).webp",
    "title": "NewsBeat",
    "companyName": "InfoPulse Media",
    "description": "Stay informed with the latest headlines, live updates, and personalized news feed.",
    "size": 38,
    "reviews": 87000,
    "ratingAvg": 4.2,
    "downloads": 6,
    "ratings": [
      { "name": "1 star", "count": 3100 },
      { "name": "2 star", "count": 5200 },
      { "name": "3 star", "count": 9700 },
      { "name": "4 star", "count": 22000 },
      { "name": "5 star", "count": 47000 }
    ]
  },
  {
    "id": 19,
    "image": "/src/assets/demo-app (1).webp",
    "title": "HealthTrack",
    "companyName": "WellnessCorp",
    "description": "Track your daily health metrics, water intake, sleep patterns and get friendly nudges to stay healthy.",
    "size": 48,
    "reviews": 95000,
    "ratingAvg": 4.4,
    "downloads": 4,
    "ratings": [
      { "name": "1 star", "count": 2700 },
      { "name": "2 star", "count": 5400 },
      { "name": "3 star", "count": 10200 },
      { "name": "4 star", "count": 26000 },
      { "name": "5 star", "count": 56800 }
    ]
  },
  {
    "id": 20,
    "image": "/src/assets/demo-app (2).webp",
    "title": "Eventify",
    "companyName": "GatherUp Inc.",
    "description": "Discover local events, buy tickets, RSVP with friends and share experiences with this social event-platform.",
    "size": 55,
    "reviews": 78000,
    "ratingAvg": 4.5,
    "downloads": 5,
    "ratings": [
      { "name": "1 star", "count": 3400 },
      { "name": "2 star", "count": 6300 },
      { "name": "3 star", "count": 12100 },
      { "name": "4 star", "count": 28300 },
      { "name": "5 star", "count": 34500 }
    ]
  }
]